grakel/__init__.py
grakel/graph.py
grakel/graph_kernels.py
grakel/tools.py
grakel/utils.py
grakel/datasets/__init__.py
grakel/datasets/base.py
grakel/datasets/testing.py
grakel/kernels/__init__.py
grakel/kernels/_c_functions.cp36-win_amd64.pyd
grakel/kernels/core_framework.py
grakel/kernels/edge_histogram.py
grakel/kernels/graph_hopper.py
grakel/kernels/graphlet_sampling.py
grakel/kernels/hadamard_code.py
grakel/kernels/kernel.py
grakel/kernels/lovasz_theta.py
grakel/kernels/multiscale_laplacian.py
grakel/kernels/neighborhood_hash.py
grakel/kernels/neighborhood_subgraph_pairwise_distance.py
grakel/kernels/odd_sth.py
grakel/kernels/propagation.py
grakel/kernels/pyramid_match.py
grakel/kernels/random_walk.py
grakel/kernels/shortest_path.py
grakel/kernels/subgraph_matching.py
grakel/kernels/svm_theta.py
grakel/kernels/vertex_histogram.py
grakel/kernels/weisfeiler_lehman.py
grakel/kernels/_isomorphism/__init__.py
grakel/kernels/_isomorphism/bliss.cp36-win_amd64.pyd
grakel/kernels/_isomorphism/intpybliss.cp36-win_amd64.pyd
grakel/tests/__init__.py
grakel/tests/__main__.py
grakel/tests/test_Kernel.py
grakel/tests/test_common.py
grakel/tests/test_graph.py
grakel/tests/test_graph_kernels.py
grakel/tests/test_kernels.py
grakel/tests/test_utils.py
grakel/tests/data/Cuneiform/Cuneiform_A.txt
grakel/tests/data/Cuneiform/Cuneiform_edge_attributes.txt
grakel/tests/data/Cuneiform/Cuneiform_edge_labels.txt
grakel/tests/data/Cuneiform/Cuneiform_graph_indicator.txt
grakel/tests/data/Cuneiform/Cuneiform_graph_labels.txt
grakel/tests/data/Cuneiform/Cuneiform_node_attributes.txt
grakel/tests/data/Cuneiform/Cuneiform_node_labels.txt
grakel/tests/data/Cuneiform/README.txt
grakel/tests/data/MUTAG/MUTAG_A.txt
grakel/tests/data/MUTAG/MUTAG_edge_labels.txt
grakel/tests/data/MUTAG/MUTAG_graph_indicator.txt
grakel/tests/data/MUTAG/MUTAG_graph_labels.txt
grakel/tests/data/MUTAG/MUTAG_node_labels.txt
grakel/tests/data/MUTAG/README.txt
grakel_dev-0.1a6.dist-info/LICENSE
grakel_dev-0.1a6.dist-info/METADATA
grakel_dev-0.1a6.dist-info/WHEEL
grakel_dev-0.1a6.dist-info/top_level.txt
grakel_dev-0.1a6.dist-info/RECORD
