Metadata-Version: 2.1
Name: grakel-dev
Version: 0.1a6
Summary: A scikit-learn compatible library for graph kernels
Home-page: https://ysig.github.io/GraKeL/dev/
Author: Ioannis Siglidis [LiX / DaSciM]
Author-email: y.siglidis@gmail.com
License: BSD
Project-URL: Documentation, https://ysig.github.io/GraKeL/dev/
Project-URL: Send us Feedback!, http://www.lix.polytechnique.fr/dascim/contact/
Project-URL: Source, https://github.com/ysig/GraKeL/tree/develop
Project-URL: Tracker, https://github.com/ysig/GraKeL/issues
Platform: UNKNOWN
Classifier: Intended Audience :: Science/Research
Classifier: Intended Audience :: Developers
Classifier: License :: OSI Approved
Classifier: Programming Language :: C
Classifier: Programming Language :: Python
Classifier: Topic :: Software Development
Classifier: Topic :: Scientific/Engineering
Classifier: Operating System :: POSIX
Classifier: Operating System :: Unix
Classifier: Operating System :: MacOS
Classifier: Programming Language :: Python :: 2.7
Classifier: Programming Language :: Python :: 3.5
Classifier: Programming Language :: Python :: 3.6
Classifier: Programming Language :: Python :: 3.7
Requires-Python: >=2.7, !=3.0.*, !=3.1.*, !=3.2.*, !=3.3.*, !=3.4.*, <4
Requires-Dist: nose (>=1.1.2)
Requires-Dist: numpy (>=1.14.0)
Requires-Dist: cython (>=0.27.3)
Requires-Dist: scikit-learn (>=0.19)
Requires-Dist: six (>=1.11.0)
Requires-Dist: future (>=0.16.0)
Provides-Extra: lovasz
Requires-Dist: cvxopt (>=1.2.0) ; extra == 'lovasz'
